topolosses/README.md
topolosses/__init__.py
topolosses/losses/__init__.py
topolosses/losses/utils.py
topolosses/losses/betti_matching/__init__.py
topolosses/losses/betti_matching/src/betti_matching.cpython-311-x86_64-linux-gnu.so
topolosses/losses/betti_matching/src/betti_matching_loss.py
topolosses/losses/betti_matching/src/ext/Betti-Matching-3D-global-build/src/BettiMatching.cpp
topolosses/losses/betti_matching/src/ext/Betti-Matching-3D-global-build/src/BettiMatching.h
topolosses/losses/betti_matching/src/ext/Betti-Matching-3D-global-build/src/_BettiMatching.cpp
topolosses/losses/betti_matching/src/ext/Betti-Matching-3D-global-build/src/config.h
topolosses/losses/betti_matching/src/ext/Betti-Matching-3D-global-build/src/data_structures.cpp
topolosses/losses/betti_matching/src/ext/Betti-Matching-3D-global-build/src/data_structures.h
topolosses/losses/betti_matching/src/ext/Betti-Matching-3D-global-build/src/main.cpp
topolosses/losses/betti_matching/src/ext/Betti-Matching-3D-global-build/src/npy.hpp
topolosses/losses/betti_matching/src/ext/Betti-Matching-3D-global-build/src/utils.cpp
topolosses/losses/betti_matching/src/ext/Betti-Matching-3D-global-build/src/utils.h
topolosses/losses/betti_matching/src/ext/Betti-Matching-3D-global-build/src/src_1D/BettiMatching.cpp
topolosses/losses/betti_matching/src/ext/Betti-Matching-3D-global-build/src/src_1D/BettiMatching.h
topolosses/losses/betti_matching/src/ext/Betti-Matching-3D-global-build/src/src_1D/data_structures.cpp
topolosses/losses/betti_matching/src/ext/Betti-Matching-3D-global-build/src/src_1D/data_structures.h
topolosses/losses/betti_matching/src/ext/Betti-Matching-3D-global-build/src/src_1D/dimension_0.cpp
topolosses/losses/betti_matching/src/ext/Betti-Matching-3D-global-build/src/src_1D/dimension_0.h
topolosses/losses/betti_matching/src/ext/Betti-Matching-3D-global-build/src/src_2D/BettiMatching.cpp
topolosses-0.2.0.dist-info/METADATA
topolosses-0.2.0.dist-info/WHEEL
topolosses-0.2.0.dist-info/RECORD
topolosses-0.2.0.dist-info/licenses/LICENSE
