Metadata-Version: 2.2
Name: topolosses
Version: 0.2.0
Summary: A collection of losses and metrics for topology-preserving image segmentation.
Author-Email: Janek Falkenstein <j.falkenstein@tum.de>
Classifier: License :: OSI Approved :: MIT License
Classifier: Programming Language :: Python
Project-URL: Repository, https://github.com/J-falkenstein/topolosses
Requires-Python: >=3.10
Requires-Dist: torch>=1.9
Requires-Dist: scipy
Requires-Dist: numpy
Requires-Dist: gudhi
Requires-Dist: POT
Requires-Dist: torchvision
Requires-Dist: opencv-python
